{
  "type": "Feature",
  "properties": {
    "gn:admin1_code":"14",
    "gn:asciiname":"Umm al Maqarin",
    "gn:country_code":"QA",
    "gn:dem":53,
    "gn:feature_class":"P",
    "gn:feature_code":"PPL",
    "gn:name":"Umm al Maq\u0101r\u012bn",
    "gn:population":0,
    "gn:timezone":"Asia/Qatar",
    "iso:country":"QA",
    "name:ara_x_preferred":[
        "\u0623\u0645 \u0627\u0644\u0645\u0642\u0627\u0631\u064a\u0646"
    ],
    "name:und_x_variant":[
        "Umm al Maq\u0101r\u012bn"
    ],
    "wof:name":"Umm al Maqarin",
    "wof:placetype":"locality"
},
  "geometry": {"coordinates":[51.18551,25.17021],"type":"Point"}
}