{
  "type": "Feature",
  "properties": {
    "iso:country":"QA",
    "name:ara_x_preferred":[
        "\u0645\u062f\u064a\u0646\u0629 \u0627\u0644\u0634\u0645\u0627\u0644"
    ],
    "name:unk_x_variant":[
        "Mad\u012bnat ash Sham\u0101l"
    ],
    "qs:gn_country":"QA",
    "qs:gn_fcode":"PPLA",
    "qs:gn_pop":0,
    "qs:name":"\u0645\u062f\u064a\u0646\u0629 \u0627\u0644\u0634\u0645\u0627\u0644",
    "qs:name_adm0":"\u0642\u0637\u0631",
    "qs:name_adm1":"\u0645\u062f\u064a\u0646\u0629 \u0627\u0644\u0634\u0645\u0627\u0644",
    "qs:photos":51,
    "qs:photos_1k":10,
    "qs:photos_9k":1,
    "qs:photos_9r":2,
    "qs:photos_all":51,
    "qs:photos_sr":2,
    "qs:placetype":"Town",
    "qs:pop_sr":"7",
    "qs:woe_adm0":23424930,
    "wof:name":"\u0645\u062f\u064a\u0646\u0629 \u0627\u0644\u0634\u0645\u0627\u0644",
    "wof:placetype":"locality"
},
  "geometry": {"coordinates":[51.2009,26.12933],"type":"Point"}
}