{
  "type": "Feature",
  "properties": {
    "gn:admin1_code":"14",
    "gn:asciiname":"As Sulaymiyah",
    "gn:country_code":"QA",
    "gn:dem":13,
    "gn:feature_class":"P",
    "gn:feature_code":"PPL",
    "gn:name":"As Sulaym\u012byah",
    "gn:population":0,
    "gn:timezone":"Asia/Qatar",
    "iso:country":"QA",
    "name:ara_x_preferred":[
        "\u0627\u0644\u0633\u064f\u0651\u0644\u064e\u064a\u0652\u0645\u0650\u064a\u064e\u0651\u0629"
    ],
    "name:und_x_variant":[
        "As Sal\u0101m\u012byah",
        "As Sulaym\u012byah"
    ],
    "wof:name":"As Sulaymiyah",
    "wof:placetype":"locality"
},
  "geometry": {"coordinates":[50.96052,25.35373],"type":"Point"}
}