{
  "type": "Feature",
  "properties": {
    "gn:admin1_code":"04",
    "gn:asciiname":"Umm Juway`id",
    "gn:country_code":"QA",
    "gn:dem":16,
    "gn:feature_class":"P",
    "gn:feature_code":"PPL",
    "gn:name":"Umm Juway\u2018id",
    "gn:population":0,
    "gn:timezone":"Asia/Qatar",
    "iso:country":"QA",
    "name:ara_x_preferred":[
        "\u0623\u064f\u0645\u0651 \u062c\u064f\u0639\u064e\u064a\u0652\u062f"
    ],
    "name:ara_x_variant":[
        "\u0623\u0645 \u062c\u0648\u064a\u0639\u062f",
        "\u0623\u064f\u0645\u0651 \u062c\u064f\u0648\u064e\u064a\u0652\u062f\u064e\u0629"
    ],
    "name:und_x_variant":[
        "Umm Ju\u2018ayd",
        "Umm Juway\u2018id",
        "Umm Juwaydah",
        "Umm Juaidah"
    ],
    "wof:name":"Umm Juway`id",
    "wof:placetype":"locality"
},
  "geometry": {"coordinates":[51.06775,25.83211],"type":"Point"}
}