{
  "type": "Feature",
  "properties": {
    "gn:admin1_code":"06",
    "gn:asciiname":"Umm Qurun",
    "gn:country_code":"QA",
    "gn:dem":43,
    "gn:feature_class":"P",
    "gn:feature_code":"PPL",
    "gn:name":"Umm Qur\u016bn",
    "gn:population":0,
    "gn:timezone":"Asia/Qatar",
    "iso:country":"QA",
    "name:ara_x_preferred":[
        "\u0623\u064f\u0645\u0651 \u0642\u064f\u0631\u064f\u0648\u0646"
    ],
    "name:ara_x_variant":[
        "Umm Qur\u016bn",
        "\u0627\u064e\u0644\u0652\u0645\u064e\u0642\u0652\u0631\u064e\u0646"
    ],
    "name:und_x_variant":[
        "Al Maqran"
    ],
    "wof:name":"Umm Qurun",
    "wof:placetype":"locality"
},
  "geometry": {"coordinates":[51.33043,25.23358],"type":"Point"}
}