{
  "type": "Feature",
  "properties": {
    "gn:admin1_code":"06",
    "gn:asciiname":"Al Waqbah",
    "gn:country_code":"QA",
    "gn:dem":33,
    "gn:feature_class":"P",
    "gn:feature_code":"PPL",
    "gn:name":"Al Waqbah",
    "gn:population":0,
    "gn:timezone":"Asia/Qatar",
    "iso:country":"QA",
    "name:ara_x_preferred":[
        "\u0627\u064e\u0644\u0652\u0648\u064e\u0642\u0652\u0628\u064e\u0629"
    ],
    "name:ceb_x_preferred":[
        "Al Wajbah"
    ],
    "name:nno_x_preferred":[
        "Al Wajbah"
    ],
    "name:und_x_variant":[
        "Al Wagbah",
        "Wajbah",
        "Al Wajba",
        "Al Waqbah"
    ],
    "wof:name":"Al Waqbah",
    "wof:placetype":"neighbourhood"
},
  "geometry": {"coordinates":[51.40142,25.30498],"type":"Point"}
}