{
  "type": "Feature",
  "properties": {
    "gn:admin1_code":"14",
    "gn:asciiname":"Abu Sidrah",
    "gn:country_code":"QA",
    "gn:dem":8,
    "gn:feature_class":"P",
    "gn:feature_code":"PPL",
    "gn:name":"Ab\u016b Sidrah",
    "gn:population":0,
    "gn:timezone":"Asia/Qatar",
    "iso:country":"QA",
    "name:ara_x_preferred":[
        "\u0623\u064e\u0628\u064f\u0648 \u0633\u0650\u062f\u0652\u0631\u064e\u0629"
    ],
    "name:ara_x_variant":[
        "\u0623\u0628\u0648 \u0633\u062f\u0631\u0629",
        "\u0628\u064f\u0648 \u0633\u0650\u062f\u0652\u0631\u064e\u0629"
    ],
    "name:und_x_variant":[
        "Ab\u016b Sidrah",
        "Busidreh",
        "B\u016b Sidrah"
    ],
    "wof:name":"Abu Sidrah",
    "wof:placetype":"locality"
},
  "geometry": {"coordinates":[51.00192,25.7251],"type":"Point"}
}