{
  "type": "Feature",
  "properties": {
    "gn:admin1_code":"04",
    "gn:asciiname":"Al Wa`b",
    "gn:country_code":"QA",
    "gn:dem":7,
    "gn:feature_class":"P",
    "gn:feature_code":"PPL",
    "gn:name":"Al Wa\u2018b",
    "gn:population":0,
    "gn:timezone":"Asia/Qatar",
    "iso:country":"QA",
    "name:ara_x_preferred":[
        "\u0627\u064e\u0644\u0652\u0648\u064e\u0639\u0652\u0628"
    ],
    "name:ara_x_variant":[
        "\u0627\u0644\u0648\u0639\u0628"
    ],
    "name:und_x_variant":[
        "Al Wa\u2018b"
    ],
    "wof:name":"Al Wa`b",
    "wof:placetype":"locality"
},
  "geometry": {"coordinates":[51.46319,25.84084],"type":"Point"}
}