{
  "type": "Feature",
  "properties": {
    "gn:admin1_code":"08",
    "gn:asciiname":"Al `Arish",
    "gn:country_code":"QA",
    "gn:dem":4,
    "gn:feature_class":"P",
    "gn:feature_code":"PPL",
    "gn:name":"Al \u2018Ar\u012bsh",
    "gn:population":0,
    "gn:timezone":"Asia/Qatar",
    "iso:country":"QA",
    "name:ara_x_preferred":[
        "\u0627\u064e\u0644\u0652\u0639\u064e\u0631\u0650\u064a\u0634"
    ],
    "name:ara_x_variant":[
        "Al \u2018Ar\u012bsh",
        "\u0627\u0644\u0639\u0631\u064a\u0634"
    ],
    "name:gle_x_preferred":[
        "Al `Arish"
    ],
    "name:nno_x_preferred":[
        "Al `Arish"
    ],
    "name:und_x_variant":[
        "\u2018Araish",
        "Al \u2018Uraysh"
    ],
    "wof:name":"Al `Arish",
    "wof:placetype":"locality"
},
  "geometry": {"coordinates":[51.05689,26.05102],"type":"Point"}
}