{
  "type": "Feature",
  "properties": {
    "gn:admin1_code":"14",
    "gn:asciiname":"`Ayn az Zughayn",
    "gn:country_code":"QA",
    "gn:dem":2,
    "gn:feature_class":"P",
    "gn:feature_code":"PPL",
    "gn:name":"\u2018Ayn az Zughayn",
    "gn:population":0,
    "gn:timezone":"Asia/Qatar",
    "iso:country":"QA",
    "name:ara_x_preferred":[
        "\u0632\u064f\u063a\u064e\u064a\u0652\u0646 \u0627\u064e\u0644\u0652\u0628\u064e\u062d\u0652\u062b"
    ],
    "name:ara_x_variant":[
        "\u0639\u064a\u0646 \u0627\u0644\u0632\u063a\u064a\u0646"
    ],
    "name:und_x_variant":[
        "Zugain al Bahath",
        "Zughayn al Ba\u1e29ath",
        "Zughayn al Ba\u1e29th",
        "\u2018Ayn az Zughayn"
    ],
    "wof:name":"`Ayn az Zughayn",
    "wof:placetype":"locality"
},
  "geometry": {"coordinates":[50.88844,25.31374],"type":"Point"}
}