{
  "type": "Feature",
  "properties": {
    "gn:admin1_code":"14",
    "gn:asciiname":"Umm az Zubar ash Sharqiyah",
    "gn:country_code":"QA",
    "gn:dem":42,
    "gn:feature_class":"P",
    "gn:feature_code":"PPL",
    "gn:name":"Umm az Zub\u0101r ash Sharq\u012byah",
    "gn:population":0,
    "gn:timezone":"Asia/Qatar",
    "iso:country":"QA",
    "name:ara_x_preferred":[
        "\u0623\u064f\u0645\u0651 \u0627\u064e\u0644\u0632\u064f\u0651\u0628\u064e\u0627\u0631"
    ],
    "name:ara_x_variant":[
        "\u0623\u0645 \u0627\u0644\u0632\u0628\u0627\u0631 \u0627\u0644\u0634\u0631\u0642\u064a\u0629"
    ],
    "name:und_x_variant":[
        "Umm az Zabar",
        "Umm az Zub\u0101r",
        "Umm az Zub\u0101r ash Sharq\u012byah"
    ],
    "wof:name":"Umm az Zubar ash Sharqiyah",
    "wof:placetype":"locality"
},
  "geometry": {"coordinates":[51.27824,25.17493],"type":"Point"}
}