{
  "type": "Feature",
  "properties": {
    "gn:admin1_code":"06",
    "gn:asciiname":"Jarayan al Batnah",
    "gn:country_code":"QA",
    "gn:dem":51,
    "gn:feature_class":"P",
    "gn:feature_code":"PPL",
    "gn:name":"Jaray\u0101n al Ba\u0163nah",
    "gn:population":0,
    "gn:timezone":"Asia/Qatar",
    "iso:country":"QA",
    "name:ara_x_preferred":[
        "\u062c\u0631\u064a\u0627\u0646 \u0627\u0644\u0628\u0637\u0646\u0629"
    ],
    "name:und_x_variant":[
        "Jaray\u0101n al Ba\u0163nah"
    ],
    "wof:name":"Jarayan al Batnah",
    "wof:placetype":"locality"
},
  "geometry": {"coordinates":[51.15298,25.1078],"type":"Point"}
}