{
  "type": "Feature",
  "properties": {
    "gn:admin1_code":"04",
    "gn:asciiname":"Al `Uqdah",
    "gn:country_code":"QA",
    "gn:dem":9,
    "gn:feature_class":"P",
    "gn:feature_code":"PPL",
    "gn:name":"Al \u2018Uqdah",
    "gn:population":0,
    "gn:timezone":"Asia/Qatar",
    "iso:country":"QA",
    "name:ara_x_preferred":[
        "\u0627\u064e\u0644\u0652\u0639\u064f\u0642\u0652\u062f\u064e\u0629"
    ],
    "name:und_x_variant":[
        "Al \u2018Uqdah"
    ],
    "wof:name":"Al `Uqdah",
    "wof:placetype":"locality"
},
  "geometry": {"coordinates":[51.46711,25.68545],"type":"Point"}
}