{
  "type": "Feature",
  "properties": {
    "gn:admin1_code":"04",
    "gn:asciiname":"Al Jatlawiyah",
    "gn:country_code":"QA",
    "gn:dem":27,
    "gn:feature_class":"P",
    "gn:feature_code":"PPL",
    "gn:name":"Al Jatl\u0101w\u012byah",
    "gn:population":0,
    "gn:timezone":"Asia/Qatar",
    "iso:country":"QA",
    "name:ara_x_preferred":[
        "\u0627\u064e\u0644\u0633\u064f\u0651\u0644\u064e\u064a\u0652\u0645\u0650\u064a \u0641\u064e\u0647\u0652\u062f \u0628\u0650\u0646 \u0639\u064e\u0628\u0652\u062f \u0627\u064e\u0644\u0644\u064e\u0651\u0670\u0647"
    ],
    "name:ara_x_variant":[
        "\u0627\u0644\u062c\u062a\u0644\u0627\u0648\u064a\u0629"
    ],
    "name:und_x_variant":[
        "As Sulaym\u012b Fahd Bin \u2018Abd All\u0101h",
        "Al Jatl\u0101w\u012byah"
    ],
    "wof:name":"Al Jatlawiyah",
    "wof:placetype":"locality"
},
  "geometry": {"coordinates":[51.20244,25.90572],"type":"Point"}
}