{
  "type": "Feature",
  "properties": {
    "iso:country":"QA",
    "name:ara_x_preferred":[
        "\u0627\u0645 \u0635\u0644\u0627\u0644 \u0645\u062d\u0645\u062f"
    ],
    "name:eng_x_preferred":[
        "Umm Salal Mohammed"
    ],
    "qs:gn_pop":0,
    "qs:name":"\u0627\u0645 \u0635\u0644\u0627\u0644 \u0645\u062d\u0645\u062f",
    "qs:name_adm0":"\u0642\u0637\u0631",
    "qs:name_adm1":"\u0623\u0645 \u0635\u0644\u0627\u0644",
    "qs:photos":179,
    "qs:photos_1k":36,
    "qs:photos_9k":1,
    "qs:photos_9r":4,
    "qs:photos_all":179,
    "qs:photos_sr":4,
    "qs:placetype":"Town",
    "qs:pop_sr":"0",
    "qs:woe_adm0":23424930,
    "wof:name":"Umm Salal Mohammed",
    "wof:placetype":"locality"
},
  "geometry": {"coordinates":[51.413231,25.418045],"type":"Point"}
}