{
  "type": "Feature",
  "properties": {
    "gn:country":"QA",
    "gn:fcode":"PPL",
    "gn:population":8380,
    "iso:country":"QA",
    "name:ara_x_preferred":[
        "\u0627\u064e\u0644\u0634\u064e\u0651\u062d\u064e\u0627\u0646\u0650\u064a\u064e\u0651\u0629"
    ],
    "name:ara_x_variant":[
        "\u0627\u0644\u0634\u064a\u062d\u0627\u0646\u064a\u0629"
    ],
    "name:und_x_variant":[
        "Al Shahaniyah"
    ],
    "qs:name":"Ash Sha\u1e29\u0101n\u012byah",
    "qs:photos_9r":0,
    "qs:photos_sr":0,
    "qs:pop_sr":"6",
    "wof:name":"Ash Sha\u1e29\u0101n\u012byah",
    "wof:placetype":"locality",
    "wof:population":8380
},
  "geometry": {"coordinates":[51.22639,25.36861],"type":"Point"}
}