{
  "type": "Feature",
  "properties": {
    "gn:admin1_code":"14",
    "gn:asciiname":"Umm al `Izam",
    "gn:country_code":"QA",
    "gn:dem":29,
    "gn:feature_class":"P",
    "gn:feature_code":"PPL",
    "gn:name":"Umm al \u2018Iz\u0327\u0101m",
    "gn:population":0,
    "gn:timezone":"Asia/Qatar",
    "iso:country":"QA",
    "name:ara_x_preferred":[
        "\u0623\u064f\u0645\u0651 \u0627\u064e\u0644\u0652\u0639\u0650\u0638\u064e\u0627\u0645"
    ],
    "name:und_x_variant":[
        "Umm al \u2018Iz\u0327\u0101m"
    ],
    "wof:name":"Umm al `Izam",
    "wof:placetype":"locality"
},
  "geometry": {"coordinates":[51.00451,25.31271],"type":"Point"}
}