{
  "type": "Feature",
  "properties": {
    "gn:admin1_code":"04",
    "gn:asciiname":"As Sulaymi Suhaym Bin Hamad",
    "gn:country_code":"QA",
    "gn:dem":35,
    "gn:feature_class":"P",
    "gn:feature_code":"PPL",
    "gn:name":"As Sulaym\u012b Su\u1e29aym Bin \u1e28amad",
    "gn:population":0,
    "gn:timezone":"Asia/Qatar",
    "iso:country":"QA",
    "name:ara_x_preferred":[
        "\u0627\u064e\u0644\u0633\u064f\u0651\u0644\u064e\u064a\u0652\u0645\u0650\u064a \u0633\u064f\u062d\u064e\u064a\u0652\u0645 \u0628\u0650\u0646 \u062d\u064e\u0645\u064e\u062f"
    ],
    "name:und_x_variant":[
        "As Sulaym\u012b Su\u1e29aym Bin \u1e28amad"
    ],
    "wof:name":"As Sulaymi Suhaym Bin Hamad",
    "wof:placetype":"locality"
},
  "geometry": {"coordinates":[51.17918,25.88112000000001],"type":"Point"}
}