{
  "type": "Feature",
  "properties": {
    "gn:admin1_code":"04",
    "gn:asciiname":"Simsimah",
    "gn:country_code":"QA",
    "gn:dem":19,
    "gn:feature_class":"P",
    "gn:feature_code":"PPL",
    "gn:name":"Simsimah",
    "gn:population":0,
    "gn:timezone":"Asia/Qatar",
    "iso:country":"QA",
    "name:ara_x_preferred":[
        "\u0633\u0650\u0645\u0652\u0633\u0650\u0645\u064e\u0629"
    ],
    "name:ara_x_variant":[
        "\u0633\u0645\u0633\u0645\u0629"
    ],
    "wof:name":"Simsimah",
    "wof:placetype":"locality"
},
  "geometry": {"coordinates":[51.40479000000001,25.79508],"type":"Point"}
}