{
  "type": "Feature",
  "properties": {
    "gn:admin1_code":"14",
    "gn:asciiname":"Al Wabrah",
    "gn:country_code":"QA",
    "gn:dem":44,
    "gn:feature_class":"P",
    "gn:feature_code":"PPL",
    "gn:name":"Al Wabrah",
    "gn:population":0,
    "gn:timezone":"Asia/Qatar",
    "iso:country":"QA",
    "name:ara_x_preferred":[
        "\u0627\u064e\u0644\u0652\u0648\u064e\u0628\u0652\u0631\u064e\u0629"
    ],
    "name:ara_x_variant":[
        "\u0627\u0644\u0648\u0628\u0631\u0629"
    ],
    "wof:name":"Al Wabrah",
    "wof:placetype":"locality"
},
  "geometry": {"coordinates":[51.17333,25.33905],"type":"Point"}
}