{
  "type": "Feature",
  "properties": {
    "gn:admin1_code":"06",
    "gn:asciiname":"Sin` al Humaydi",
    "gn:country_code":"QA",
    "gn:dem":24,
    "gn:feature_class":"P",
    "gn:feature_code":"PPL",
    "gn:name":"\u015ein\u2018 al \u1e28umayd\u012b",
    "gn:population":0,
    "gn:timezone":"Asia/Qatar",
    "iso:country":"QA",
    "name:ara_x_preferred":[
        "\u0635\u0646\u0639 \u0627\u0644\u062d\u0645\u064a\u062f\u064a"
    ],
    "name:und_x_variant":[
        "\u015ein\u2018 al \u1e28umayd\u012b"
    ],
    "wof:name":"Sin` al Humaydi",
    "wof:placetype":"locality"
},
  "geometry": {"coordinates":[51.33689,25.3697],"type":"Point"}
}