{
  "type": "Feature",
  "properties": {
    "gn:admin1_code":"14",
    "gn:asciiname":"Abu Nakhlah",
    "gn:country_code":"QA",
    "gn:dem":47,
    "gn:feature_class":"P",
    "gn:feature_code":"PPL",
    "gn:name":"Ab\u016b Nakhlah",
    "gn:population":0,
    "gn:timezone":"Asia/Qatar",
    "iso:country":"QA",
    "name:ara_x_preferred":[
        "\u0623\u0628\u0648 \u0646\u062e\u0644\u0629"
    ],
    "name:und_x_variant":[
        "Ab\u016b Nakhlah"
    ],
    "wof:name":"Abu Nakhlah",
    "wof:placetype":"locality"
},
  "geometry": {"coordinates":[51.31733,25.17386],"type":"Point"}
}