{
  "type": "Feature",
  "properties": {
    "gn:admin1_code":"10",
    "gn:asciiname":"Turaynah",
    "gn:country_code":"QA",
    "gn:dem":45,
    "gn:feature_class":"P",
    "gn:feature_code":"PPL",
    "gn:name":"Turaynah",
    "gn:population":0,
    "gn:timezone":"Asia/Qatar",
    "iso:country":"QA",
    "name:ara_x_preferred":[
        "\u0645\u064e\u0632\u0652\u0631\u064e\u0639\u064e\u0629 \u062a\u064f\u0631\u064e\u064a\u0652\u0646\u064e\u0627"
    ],
    "name:ara_x_variant":[
        "\u062a\u0631\u064a\u0646\u0629",
        "\u062a\u0631\u064a\u0646\u062d\u0629"
    ],
    "name:und_x_variant":[
        "Mazra\u2018at Tar\u012bn\u0101",
        "Mazra\u2018at Turayn\u0101",
        "Turaynah",
        "Turayn\u1e29ah"
    ],
    "wof:name":"Turaynah",
    "wof:placetype":"locality"
},
  "geometry": {"coordinates":[51.2107,24.75809],"type":"Point"}
}