{
  "type": "Feature",
  "properties": {
    "gn:admin1_code":"14",
    "gn:asciiname":"Umm Ghuwaylinah",
    "gn:country_code":"QA",
    "gn:dem":34,
    "gn:feature_class":"P",
    "gn:feature_code":"PPL",
    "gn:name":"Umm Ghuwayl\u012bnah",
    "gn:population":0,
    "gn:timezone":"Asia/Qatar",
    "iso:country":"QA",
    "name:ara_x_preferred":[
        "\u0623\u064f\u0645\u0651 \u063a\u064f\u0648\u064e\u064a\u0652\u0644\u0650\u064a\u0646\u064e\u0629"
    ],
    "name:und_x_variant":[
        "Umm Ghuwayl\u012bn\u0101",
        "Umm Ghuwayl\u012bnah"
    ],
    "wof:name":"Umm Ghuwaylinah",
    "wof:placetype":"locality"
},
  "geometry": {"coordinates":[51.14986,25.58716],"type":"Point"}
}