{
  "type": "Feature",
  "properties": {
    "gn:admin1_code":"08",
    "gn:asciiname":"Umm Sabbah",
    "gn:country_code":"QA",
    "gn:dem":8,
    "gn:feature_class":"P",
    "gn:feature_code":"PPL",
    "gn:name":"Umm \u015eabb\u0101\u1e29",
    "gn:population":0,
    "gn:timezone":"Asia/Qatar",
    "iso:country":"QA",
    "name:ara_x_preferred":[
        "\u0623\u064f\u0645\u0651 \u0635\u064e\u0628\u064e\u0651\u0627\u062d"
    ],
    "name:und_x_variant":[
        "Umm \u015eabb\u0101\u1e29"
    ],
    "wof:name":"Umm Sabbah",
    "wof:placetype":"locality"
},
  "geometry": {"coordinates":[51.18966,26.11094],"type":"Point"}
}