{
  "type": "Feature",
  "properties": {
    "gn:admin1_code":"06",
    "gn:asciiname":"Al Kir`anah",
    "gn:country_code":"QA",
    "gn:dem":41,
    "gn:feature_class":"P",
    "gn:feature_code":"PPL",
    "gn:name":"Al Kir\u2018\u0101nah",
    "gn:population":0,
    "gn:timezone":"Asia/Qatar",
    "iso:country":"QA",
    "name:ara_x_preferred":[
        "\u0627\u064e\u0644\u0652\u0643\u0650\u0631\u0652\u0639\u064e\u0627\u0646\u064e\u0629"
    ],
    "name:ara_x_variant":[
        "\u0627\u0644\u0643\u0631\u0639\u0627\u0646\u0629"
    ],
    "name:und_x_variant":[
        "Kar\u2018\u0101nah",
        "Al Kir\u2018\u0101nah"
    ],
    "wof:name":"Al Kir`anah",
    "wof:placetype":"locality"
},
  "geometry": {"coordinates":[51.04324,25.01108],"type":"Point"}
}